AutoEDA/AutoEDA.py
AutoEDA/__init__.py
MLAutoEDA/MLAutoEDA.py
MLAutoEDA/__init__.py
MLAutoEDA-0.2.0.dist-info/LICENSE
MLAutoEDA-0.2.0.dist-info/METADATA
MLAutoEDA-0.2.0.dist-info/WHEEL
MLAutoEDA-0.2.0.dist-info/top_level.txt
MLAutoEDA-0.2.0.dist-info/RECORD
