Metadata-Version: 2.1
Name: MLAutoEDA
Version: 0.2.0
Summary: Helper functions to automate Exploratory Data Analysis. The focus is mainly on typical Machine Learning datasets, where there is a target variable (numerical or categorical) and the aim of EDA is to get a sense of the data and whether the variables may be useful for the prediction or not.
Home-page: UNKNOWN
Author: Edoardo Vivo
Author-email: vivoedoardo@gmail.com
License: MIT
Platform: UNKNOWN
Classifier: Intended Audience :: Developers
Classifier: License :: OSI Approved :: MIT License
Classifier: Programming Language :: Python
Classifier: Programming Language :: Python :: 3
Classifier: Programming Language :: Python :: 3.6
Classifier: Programming Language :: Python :: 3.7
Classifier: Programming Language :: Python :: 3.8
Classifier: Programming Language :: Python :: 3.9
Classifier: Operating System :: OS Independent
Requires-Dist: numpy
Requires-Dist: pandas
Requires-Dist: matplotlib
Requires-Dist: seaborn
Requires-Dist: scipy
Requires-Dist: statsmodels
